dicer/__init__.py
dicer/__version__.py
dicer/data_exception.py
dicer/hyper_dicer.py
dicer/keycloak_rest_client.py
dicer/main.py
dicer/query_results.py
dicer/transmart.py
dicer/transmart_rest_client.py
dicer/mappers/mapper_helper.py
dicer/mappers/observation_mapper.py
dicer/mappers/ontology_mapper.py
dicer/mappers/patient_mapper.py
dicer/mappers/transmart_loader_mapper.py
transmart_hyper_dicer-0.1.3.dist-info/LICENSE
transmart_hyper_dicer-0.1.3.dist-info/METADATA
transmart_hyper_dicer-0.1.3.dist-info/WHEEL
transmart_hyper_dicer-0.1.3.dist-info/entry_points.txt
transmart_hyper_dicer-0.1.3.dist-info/top_level.txt
transmart_hyper_dicer-0.1.3.dist-info/RECORD
