Metadata-Version: 2.1
Name: transmart-hyper-dicer
Version: 0.1.3
Summary: Data slicing tool for reading data from one tranSMART and uploading it to another
Home-page: https://github.com/thehyve/transmart-hyper-dicer
Author: Ewelina Grudzien
Author-email: ewelina@thehyve.nl
License: MIT
Keywords: transmart-hyper-dicer,transmart
Platform: UNKNOWN
Classifier: Development Status :: 2 - Pre-Alpha
Classifier: Intended Audience :: Developers
Classifier: Topic :: Scientific/Engineering :: Bio-Informatics
Classifier: License :: OSI Approved :: MIT License
Classifier: Natural Language :: English
Classifier: Programming Language :: Python :: 3
Classifier: Programming Language :: Python :: 3.6
Classifier: Programming Language :: Python :: 3.7
Requires-Python: >=3.6.0
Requires-Dist: click (==7.0)
Requires-Dist: pandas (<0.26,>=0.25)
Requires-Dist: pydantic (<0.33,>=0.32)
Requires-Dist: python-dotenv (==0.10.3)
Requires-Dist: PyYAML (<5.2,>=5.1)
Requires-Dist: requests (==2.22.0)
Requires-Dist: transmart-loader (==1.3.3)
Provides-Extra: dev
Requires-Dist: prospector[with_pyroma] ; extra == 'dev'
Requires-Dist: pygments ; extra == 'dev'
Requires-Dist: yapf ; extra == 'dev'
Requires-Dist: isort ; extra == 'dev'
